causalexplain/__init__.py
causalexplain/__main__.py
causalexplain/_version.py
causalexplain/causalexplainer.py
causalexplain/common/__init__.py
causalexplain/common/metrics_config.py
causalexplain/common/notebook.py
causalexplain/common/plot.py
causalexplain/common/utils.py
causalexplain/estimators/__init__.py
causalexplain/estimators/cam/__init__.py
causalexplain/estimators/cam/cam.py
causalexplain/estimators/cam/computeScoreMat.py
causalexplain/estimators/cam/computeScoreMatParallel.py
causalexplain/estimators/cam/pruning.py
causalexplain/estimators/cam/selGam.py
causalexplain/estimators/cam/selGamBoost.py
causalexplain/estimators/cam/selLasso.py
causalexplain/estimators/cam/selLm.py
causalexplain/estimators/cam/selLmBoost.py
causalexplain/estimators/cam/train_GAMboost.py
causalexplain/estimators/cam/train_LMboost.py
causalexplain/estimators/cam/train_gam.py
causalexplain/estimators/cam/train_gp.py
causalexplain/estimators/cam/train_lasso.py
causalexplain/estimators/cam/train_linear.py
causalexplain/estimators/cam/updateScoreMat.py
causalexplain/estimators/fci/__init__.py
causalexplain/estimators/fci/fci.py
causalexplain/estimators/ges/__init__.py
causalexplain/estimators/ges/decomposable_score.py
causalexplain/estimators/ges/ges.py
causalexplain/estimators/ges/scores.py
causalexplain/estimators/ges/utils.py
causalexplain/estimators/lingam/__init__.py
causalexplain/estimators/lingam/base.py
causalexplain/estimators/lingam/bootstrap.py
causalexplain/estimators/lingam/lingam.py
causalexplain/estimators/lingam/utils.py
causalexplain/estimators/notears/__init__.py
causalexplain/estimators/notears/lbfgsb_scipy.py
causalexplain/estimators/notears/linear.py
causalexplain/estimators/notears/locally_connected.py
causalexplain/estimators/notears/loss.py
causalexplain/estimators/notears/main.py
causalexplain/estimators/notears/nonlinear.py
causalexplain/estimators/notears/notears.py
causalexplain/estimators/notears/trace_expm.py
causalexplain/estimators/notears/utils.py
causalexplain-0.9.1.dist-info/METADATA
causalexplain-0.9.1.dist-info/WHEEL
causalexplain-0.9.1.dist-info/top_level.txt
causalexplain-0.9.1.dist-info/RECORD
